{"targets":[{"id":"wn./J{q-;Tv`7nPS+tbv","name":"Stage","isStage":true,"x":0,"y":0,"size":100,"direction":90,"draggable":false,"currentCostume":0,"costume":{"skinId":5,"name":"backdrop1","bitmapResolution":1,"rotationCenterX":240,"rotationCenterY":180,"dataFormat":"png","assetId":"739b5e2a2435f6e1ec2993791b423146"},"costumeCount":1,"visible":true,"rotationStyle":"all around","blocks":{},"variables":{"au-_Kf`#mvf-/bwi3#k*-count":{"id":"au-_Kf`#mvf-/bwi3#k*-count","name":"count","type":"","value":0}},"lists":{},"costumes":[{"skinId":5,"name":"backdrop1","bitmapResolution":1,"rotationCenterX":240,"rotationCenterY":180,"dataFormat":"png","assetId":"739b5e2a2435f6e1ec2993791b423146"}],"sounds":[{"format":"","rate":11025,"sampleCount":258,"soundID":1,"name":"pop","md5":"83a9787d4cb6f3b7632b4ddfebf74367.wav","data":null,"dataFormat":"wav","assetId":"83a9787d4cb6f3b7632b4ddfebf74367","soundId":"!:ium[c,ojX}EG^G/bo8"}]},{"id":"L#4mjY6~W7*PA||=)3Va","name":"Sprite1","isStage":false,"x":0,"y":0,"size":100,"direction":90,"draggable":false,"currentCostume":0,"costume":{"skinId":3,"name":"costume1","bitmapResolution":1,"rotationCenterX":47,"rotationCenterY":55,"dataFormat":"svg","assetId":"09dc888b0b7df19f70d81588ae73420e"},"costumeCount":2,"visible":true,"rotationStyle":"all around","blocks":{"3Vcrw^|U55kM1T#o5[M~":{"id":"3Vcrw^|U55kM1T#o5[M~","opcode":"event_whenflagclicked","inputs":{},"fields":{},"next":"]Y(.BK{YnGq|.Y8X`3I?","topLevel":true,"parent":null,"shadow":false,"x":178,"y":166},"]Y(.BK{YnGq|.Y8X`3I?":{"id":"]Y(.BK{YnGq|.Y8X`3I?","opcode":"MicroBit.showstring","inputs":{"STR":{"name":"STR","block":"$/Q~2te7UEuR,tX]aRGz","shadow":"$/Q~2te7UEuR,tX]aRGz"}},"fields":{},"next":"GLPgk2FDp+~JWVR^u^cT","topLevel":false,"parent":"3Vcrw^|U55kM1T#o5[M~","shadow":false},"$/Q~2te7UEuR,tX]aRGz":{"id":"$/Q~2te7UEuR,tX]aRGz","opcode":"text","inputs":{},"fields":{"TEXT":{"name":"TEXT","value":"3"}},"next":null,"topLevel":false,"parent":"]Y(.BK{YnGq|.Y8X`3I?","shadow":true},"GLPgk2FDp+~JWVR^u^cT":{"id":"GLPgk2FDp+~JWVR^u^cT","opcode":"control_wait","inputs":{"DURATION":{"name":"DURATION","block":"4Yh0w0la]z_GRTHs6ewK","shadow":"4Yh0w0la]z_GRTHs6ewK"}},"fields":{},"next":"!Fd*g)-yd-x^q]@zej(x","topLevel":false,"parent":"]Y(.BK{YnGq|.Y8X`3I?","shadow":false},"4Yh0w0la]z_GRTHs6ewK":{"id":"4Yh0w0la]z_GRTHs6ewK","opcode":"math_positive_number","inputs":{},"fields":{"NUM":{"name":"NUM","value":"1"}},"next":null,"topLevel":false,"parent":"GLPgk2FDp+~JWVR^u^cT","shadow":true},"!Fd*g)-yd-x^q]@zej(x":{"id":"!Fd*g)-yd-x^q]@zej(x","opcode":"MicroBit.showstring","inputs":{"STR":{"name":"STR","block":"v*j0(YqTlXDIsypBa2Lj","shadow":"v*j0(YqTlXDIsypBa2Lj"}},"fields":{},"next":"09@a^xB`!b6/,88~]O]G","topLevel":false,"parent":"GLPgk2FDp+~JWVR^u^cT","shadow":false},"v*j0(YqTlXDIsypBa2Lj":{"id":"v*j0(YqTlXDIsypBa2Lj","opcode":"text","inputs":{},"fields":{"TEXT":{"name":"TEXT","value":"2"}},"next":null,"topLevel":false,"parent":"!Fd*g)-yd-x^q]@zej(x","shadow":true},"09@a^xB`!b6/,88~]O]G":{"id":"09@a^xB`!b6/,88~]O]G","opcode":"control_wait","inputs":{"DURATION":{"name":"DURATION","block":"]y0tu|9P_A+KZEUq]W$G","shadow":"]y0tu|9P_A+KZEUq]W$G"}},"fields":{},"next":"m:ENTT^/oq5oFk_CmO3`","topLevel":false,"parent":"!Fd*g)-yd-x^q]@zej(x","shadow":false},"]y0tu|9P_A+KZEUq]W$G":{"id":"]y0tu|9P_A+KZEUq]W$G","opcode":"math_positive_number","inputs":{},"fields":{"NUM":{"name":"NUM","value":"1"}},"next":null,"topLevel":false,"parent":"09@a^xB`!b6/,88~]O]G","shadow":true},"m:ENTT^/oq5oFk_CmO3`":{"id":"m:ENTT^/oq5oFk_CmO3`","opcode":"MicroBit.showstring","inputs":{"STR":{"name":"STR","block":"Yr6wI1,:AAYDEo/]z1^r","shadow":"Yr6wI1,:AAYDEo/]z1^r"}},"fields":{},"next":"YFdQon$x=(`@C[S3Shv.","topLevel":false,"parent":"09@a^xB`!b6/,88~]O]G","shadow":false},"Yr6wI1,:AAYDEo/]z1^r":{"id":"Yr6wI1,:AAYDEo/]z1^r","opcode":"text","inputs":{},"fields":{"TEXT":{"name":"TEXT","value":"1"}},"next":null,"topLevel":false,"parent":"m:ENTT^/oq5oFk_CmO3`","shadow":true},"YFdQon$x=(`@C[S3Shv.":{"id":"YFdQon$x=(`@C[S3Shv.","opcode":"control_wait","inputs":{"DURATION":{"name":"DURATION","block":"Zv@QL@:s}40|od;Qb~O9","shadow":"Zv@QL@:s}40|od;Qb~O9"}},"fields":{},"next":"iI9NR+0sfwnx!NjuE`g+","topLevel":false,"parent":"m:ENTT^/oq5oFk_CmO3`","shadow":false},"Zv@QL@:s}40|od;Qb~O9":{"id":"Zv@QL@:s}40|od;Qb~O9","opcode":"math_positive_number","inputs":{},"fields":{"NUM":{"name":"NUM","value":"1"}},"next":null,"topLevel":false,"parent":"YFdQon$x=(`@C[S3Shv.","shadow":true},"iI9NR+0sfwnx!NjuE`g+":{"id":"iI9NR+0sfwnx!NjuE`g+","opcode":"MicroBit.showledmat","inputs":{"ICON":{"name":"ICON","block":"|6csJfnwa(NxQ-tCFD9f","shadow":"|6csJfnwa(NxQ-tCFD9f"}},"fields":{},"next":"S7@Y97gY)b.gA0}=o$G=","topLevel":false,"parent":"YFdQon$x=(`@C[S3Shv.","shadow":false},"|6csJfnwa(NxQ-tCFD9f":{"id":"|6csJfnwa(NxQ-tCFD9f","opcode":"bit_leds","inputs":{},"fields":{"TEXT":{"name":"TEXT","value":"90009:09090:00900:09090:90009"}},"next":null,"topLevel":false,"parent":"iI9NR+0sfwnx!NjuE`g+","shadow":true},"S7@Y97gY)b.gA0}=o$G=":{"id":"S7@Y97gY)b.gA0}=o$G=","opcode":"control_wait","inputs":{"DURATION":{"name":"DURATION","block":"!7W);noYeZx?(*xP%_n{","shadow":"!7W);noYeZx?(*xP%_n{"}},"fields":{},"next":"Pehdgw,nlTLNkD(g$?iu","topLevel":false,"parent":"iI9NR+0sfwnx!NjuE`g+","shadow":false},"!7W);noYeZx?(*xP%_n{":{"id":"!7W);noYeZx?(*xP%_n{","opcode":"math_positive_number","inputs":{},"fields":{"NUM":{"name":"NUM","value":"2"}},"next":null,"topLevel":false,"parent":"S7@Y97gY)b.gA0}=o$G=","shadow":true},"Pehdgw,nlTLNkD(g$?iu":{"id":"Pehdgw,nlTLNkD(g$?iu","opcode":"control_forever","inputs":{"SUBSTACK":{"name":"SUBSTACK","block":"])pE!c)Y:~x.bU`?Da.i","shadow":null}},"fields":{},"next":null,"topLevel":false,"parent":"S7@Y97gY)b.gA0}=o$G=","shadow":false},"])pE!c)Y:~x.bU`?Da.i":{"id":"])pE!c)Y:~x.bU`?Da.i","opcode":"MicroBit.showledmat","inputs":{"ICON":{"name":"ICON","block":"uBVe5A/C2i%Fo{7tV-F5","shadow":"uBVe5A/C2i%Fo{7tV-F5"}},"fields":{},"next":"FrEC?`qn4hyuwR$F!w7~","topLevel":false,"parent":"Pehdgw,nlTLNkD(g$?iu","shadow":false},"uBVe5A/C2i%Fo{7tV-F5":{"id":"uBVe5A/C2i%Fo{7tV-F5","opcode":"bit_leds","inputs":{},"fields":{"TEXT":{"name":"TEXT","value":"00900:00900:00900:00900:00900"}},"next":null,"topLevel":false,"parent":"])pE!c)Y:~x.bU`?Da.i","shadow":true},"FrEC?`qn4hyuwR$F!w7~":{"id":"FrEC?`qn4hyuwR$F!w7~","opcode":"control_wait","inputs":{"DURATION":{"name":"DURATION","block":"x|z0G*(t(Eez/!D3H8%(","shadow":"x|z0G*(t(Eez/!D3H8%("}},"fields":{},"next":"kTvH)UVayy$9wYqr?Y^:","topLevel":false,"parent":"])pE!c)Y:~x.bU`?Da.i","shadow":false},"x|z0G*(t(Eez/!D3H8%(":{"id":"x|z0G*(t(Eez/!D3H8%(","opcode":"math_positive_number","inputs":{},"fields":{"NUM":{"name":"NUM","value":"0.1"}},"next":null,"topLevel":false,"parent":"FrEC?`qn4hyuwR$F!w7~","shadow":true},"kTvH)UVayy$9wYqr?Y^:":{"id":"kTvH)UVayy$9wYqr?Y^:","opcode":"MicroBit.showledmat","inputs":{"ICON":{"name":"ICON","block":"l-2~Ktc:k?1[IBWKdoT]","shadow":"l-2~Ktc:k?1[IBWKdoT]"}},"fields":{},"next":"]ylDfg~TzbU1LbL=n5Q7","topLevel":false,"parent":"FrEC?`qn4hyuwR$F!w7~","shadow":false},"l-2~Ktc:k?1[IBWKdoT]":{"id":"l-2~Ktc:k?1[IBWKdoT]","opcode":"bit_leds","inputs":{},"fields":{"TEXT":{"name":"TEXT","value":"00009:00090:00900:09000:90000"}},"next":null,"topLevel":false,"parent":"kTvH)UVayy$9wYqr?Y^:","shadow":true},"]ylDfg~TzbU1LbL=n5Q7":{"id":"]ylDfg~TzbU1LbL=n5Q7","opcode":"control_wait","inputs":{"DURATION":{"name":"DURATION","block":"Yi8bF3NC8tyO#2r#0u;p","shadow":"Yi8bF3NC8tyO#2r#0u;p"}},"fields":{},"next":"Hpb#C1B#p@Fh/Mx6(p?1","topLevel":false,"parent":"kTvH)UVayy$9wYqr?Y^:","shadow":false},"Yi8bF3NC8tyO#2r#0u;p":{"id":"Yi8bF3NC8tyO#2r#0u;p","opcode":"math_positive_number","inputs":{},"fields":{"NUM":{"name":"NUM","value":"0.1"}},"next":null,"topLevel":false,"parent":"]ylDfg~TzbU1LbL=n5Q7","shadow":true},"Hpb#C1B#p@Fh/Mx6(p?1":{"id":"Hpb#C1B#p@Fh/Mx6(p?1","opcode":"MicroBit.showledmat","inputs":{"ICON":{"name":"ICON","block":"xYE@aNwa12gIOxxD;gd!","shadow":"xYE@aNwa12gIOxxD;gd!"}},"fields":{},"next":"F3l8@s2l;?9(ouqT71_[","topLevel":false,"parent":"]ylDfg~TzbU1LbL=n5Q7","shadow":false},"xYE@aNwa12gIOxxD;gd!":{"id":"xYE@aNwa12gIOxxD;gd!","opcode":"bit_leds","inputs":{},"fields":{"TEXT":{"name":"TEXT","value":"00000:00000:99999:00000:00000"}},"next":null,"topLevel":false,"parent":"Hpb#C1B#p@Fh/Mx6(p?1","shadow":true},"F3l8@s2l;?9(ouqT71_[":{"id":"F3l8@s2l;?9(ouqT71_[","opcode":"control_wait","inputs":{"DURATION":{"name":"DURATION","block":"Mgc08Mt]N@f!2B#I8.[u","shadow":"Mgc08Mt]N@f!2B#I8.[u"}},"fields":{},"next":"qA^f7!lGh)3v_Mx]efs*","topLevel":false,"parent":"Hpb#C1B#p@Fh/Mx6(p?1","shadow":false},"Mgc08Mt]N@f!2B#I8.[u":{"id":"Mgc08Mt]N@f!2B#I8.[u","opcode":"math_positive_number","inputs":{},"fields":{"NUM":{"name":"NUM","value":"0.1"}},"next":null,"topLevel":false,"parent":"F3l8@s2l;?9(ouqT71_[","shadow":true},"qA^f7!lGh)3v_Mx]efs*":{"id":"qA^f7!lGh)3v_Mx]efs*","opcode":"MicroBit.showledmat","inputs":{"ICON":{"name":"ICON","block":"2zkU,O2f52k!q8-G;{@t","shadow":"2zkU,O2f52k!q8-G;{@t"}},"fields":{},"next":"]wAUgCbV[H!gI~_.$!QR","topLevel":false,"parent":"F3l8@s2l;?9(ouqT71_[","shadow":false},"2zkU,O2f52k!q8-G;{@t":{"id":"2zkU,O2f52k!q8-G;{@t","opcode":"bit_leds","inputs":{},"fields":{"TEXT":{"name":"TEXT","value":"90000:09000:00900:00090:00009"}},"next":null,"topLevel":false,"parent":"qA^f7!lGh)3v_Mx]efs*","shadow":true},"]wAUgCbV[H!gI~_.$!QR":{"id":"]wAUgCbV[H!gI~_.$!QR","opcode":"control_wait","inputs":{"DURATION":{"name":"DURATION","block":"~!myS~T!A4|_K7yI6oT7","shadow":"~!myS~T!A4|_K7yI6oT7"}},"fields":{},"next":"?/{,/JS8Pw4dtS91BvPd","topLevel":false,"parent":"qA^f7!lGh)3v_Mx]efs*","shadow":false},"~!myS~T!A4|_K7yI6oT7":{"id":"~!myS~T!A4|_K7yI6oT7","opcode":"math_positive_number","inputs":{},"fields":{"NUM":{"name":"NUM","value":"0.1"}},"next":null,"topLevel":false,"parent":"]wAUgCbV[H!gI~_.$!QR","shadow":true},"?/{,/JS8Pw4dtS91BvPd":{"id":"?/{,/JS8Pw4dtS91BvPd","opcode":"MicroBit.showledmat","inputs":{"ICON":{"name":"ICON","block":"HA|3I4Fgf,}#,gw{1WAl","shadow":"HA|3I4Fgf,}#,gw{1WAl"}},"fields":{},"next":"FTeMIVV=#lSi*ZT^PUNz","topLevel":false,"parent":"]wAUgCbV[H!gI~_.$!QR","shadow":false},"HA|3I4Fgf,}#,gw{1WAl":{"id":"HA|3I4Fgf,}#,gw{1WAl","opcode":"bit_leds","inputs":{},"fields":{"TEXT":{"name":"TEXT","value":"00900:00900:00900:00900:00900"}},"next":null,"topLevel":false,"parent":"?/{,/JS8Pw4dtS91BvPd","shadow":true},"FTeMIVV=#lSi*ZT^PUNz":{"id":"FTeMIVV=#lSi*ZT^PUNz","opcode":"control_wait","inputs":{"DURATION":{"name":"DURATION","block":"0sk~LA^g-?M0M9)V|#U+","shadow":"0sk~LA^g-?M0M9)V|#U+"}},"fields":{},"next":"3+#fdo{sAuR5X5I+o]X0","topLevel":false,"parent":"?/{,/JS8Pw4dtS91BvPd","shadow":false},"0sk~LA^g-?M0M9)V|#U+":{"id":"0sk~LA^g-?M0M9)V|#U+","opcode":"math_positive_number","inputs":{},"fields":{"NUM":{"name":"NUM","value":"0.1"}},"next":null,"topLevel":false,"parent":"FTeMIVV=#lSi*ZT^PUNz","shadow":true},"3+#fdo{sAuR5X5I+o]X0":{"id":"3+#fdo{sAuR5X5I+o]X0","opcode":"MicroBit.showledmat","inputs":{"ICON":{"name":"ICON","block":"jtb{X!pd!0$=Cy?a}Lak","shadow":"jtb{X!pd!0$=Cy?a}Lak"}},"fields":{},"next":"*cbHCY]*c.v%M{h}3AO~","topLevel":false,"parent":"FTeMIVV=#lSi*ZT^PUNz","shadow":false},"jtb{X!pd!0$=Cy?a}Lak":{"id":"jtb{X!pd!0$=Cy?a}Lak","opcode":"bit_leds","inputs":{},"fields":{"TEXT":{"name":"TEXT","value":"00009:00090:00900:09000:90000"}},"next":null,"topLevel":false,"parent":"3+#fdo{sAuR5X5I+o]X0","shadow":true},"*cbHCY]*c.v%M{h}3AO~":{"id":"*cbHCY]*c.v%M{h}3AO~","opcode":"control_wait","inputs":{"DURATION":{"name":"DURATION","block":"%S6-3d}vPTQY*suq)R-F","shadow":"%S6-3d}vPTQY*suq)R-F"}},"fields":{},"next":"7;,9Uda3gdz$0MGfw.7.","topLevel":false,"parent":"3+#fdo{sAuR5X5I+o]X0","shadow":false},"%S6-3d}vPTQY*suq)R-F":{"id":"%S6-3d}vPTQY*suq)R-F","opcode":"math_positive_number","inputs":{},"fields":{"NUM":{"name":"NUM","value":"0.1"}},"next":null,"topLevel":false,"parent":"*cbHCY]*c.v%M{h}3AO~","shadow":true},"7;,9Uda3gdz$0MGfw.7.":{"id":"7;,9Uda3gdz$0MGfw.7.","opcode":"MicroBit.showledmat","inputs":{"ICON":{"name":"ICON","block":"E+E^p7/T.()FWGv[C)f1","shadow":"E+E^p7/T.()FWGv[C)f1"}},"fields":{},"next":"OQZ(U(aK!@.fANK.V=+O","topLevel":false,"parent":"*cbHCY]*c.v%M{h}3AO~","shadow":false},"E+E^p7/T.()FWGv[C)f1":{"id":"E+E^p7/T.()FWGv[C)f1","opcode":"bit_leds","inputs":{},"fields":{"TEXT":{"name":"TEXT","value":"00000:00000:99999:00000:00000"}},"next":null,"topLevel":false,"parent":"7;,9Uda3gdz$0MGfw.7.","shadow":true},"OQZ(U(aK!@.fANK.V=+O":{"id":"OQZ(U(aK!@.fANK.V=+O","opcode":"control_wait","inputs":{"DURATION":{"name":"DURATION","block":"!XI{HPhxZ`%g%:/X8?#p","shadow":"!XI{HPhxZ`%g%:/X8?#p"}},"fields":{},"next":"IvJUHCsXuf_b6=(NA(b/","topLevel":false,"parent":"7;,9Uda3gdz$0MGfw.7.","shadow":false},"!XI{HPhxZ`%g%:/X8?#p":{"id":"!XI{HPhxZ`%g%:/X8?#p","opcode":"math_positive_number","inputs":{},"fields":{"NUM":{"name":"NUM","value":"0.1"}},"next":null,"topLevel":false,"parent":"OQZ(U(aK!@.fANK.V=+O","shadow":true},"IvJUHCsXuf_b6=(NA(b/":{"id":"IvJUHCsXuf_b6=(NA(b/","opcode":"MicroBit.showledmat","inputs":{"ICON":{"name":"ICON","block":"Q9UOg}n`cg,]ysV7BMB_","shadow":"Q9UOg}n`cg,]ysV7BMB_"}},"fields":{},"next":"h#M59pes4`GB(t2u_Uy*","topLevel":false,"parent":"OQZ(U(aK!@.fANK.V=+O","shadow":false},"Q9UOg}n`cg,]ysV7BMB_":{"id":"Q9UOg}n`cg,]ysV7BMB_","opcode":"bit_leds","inputs":{},"fields":{"TEXT":{"name":"TEXT","value":"90000:09000:00900:00090:00009"}},"next":null,"topLevel":false,"parent":"IvJUHCsXuf_b6=(NA(b/","shadow":true},"h#M59pes4`GB(t2u_Uy*":{"id":"h#M59pes4`GB(t2u_Uy*","opcode":"control_wait","inputs":{"DURATION":{"name":"DURATION","block":"4D4YhSue`NL0Dh;B:AGe","shadow":"4D4YhSue`NL0Dh;B:AGe"}},"fields":{},"next":null,"topLevel":false,"parent":"IvJUHCsXuf_b6=(NA(b/","shadow":false},"4D4YhSue`NL0Dh;B:AGe":{"id":"4D4YhSue`NL0Dh;B:AGe","opcode":"math_positive_number","inputs":{},"fields":{"NUM":{"name":"NUM","value":"0.1"}},"next":null,"topLevel":false,"parent":"h#M59pes4`GB(t2u_Uy*","shadow":true}},"variables":{},"lists":{},"costumes":[{"skinId":3,"name":"costume1","bitmapResolution":1,"rotationCenterX":47,"rotationCenterY":55,"dataFormat":"svg","assetId":"09dc888b0b7df19f70d81588ae73420e"},{"skinId":4,"name":"costume2","bitmapResolution":1,"rotationCenterX":47,"rotationCenterY":55,"dataFormat":"svg","assetId":"3696356a03a8d938318876a593572843"}],"sounds":[{"format":"","rate":22050,"sampleCount":18688,"soundID":0,"name":"Meow","md5":"83c36d806dc92327b9e7049a565c6bff.wav","data":null,"dataFormat":"wav","assetId":"83c36d806dc92327b9e7049a565c6bff","soundId":"z5_{^zbq}C;PRuE7@N96"}]}],"meta":{"semver":"3.0.0","vm":"0.1.0","agent":"Mozilla/5.0 (Windows NT 6.1; WOW64) AppleWebKit/537.36 (KHTML, like Gecko) Kittenblock/1.6.1 Chrome/58.0.3029.110 Electron/1.7.10 Safari/537.36"}}