{"targets":[{"id":"9nCyN5f6o;VaN@]D=otL","name":"Stage","isStage":true,"x":0,"y":0,"size":100,"direction":90,"draggable":false,"currentCostume":0,"costume":{"name":"backdrop1","bitmapResolution":1,"rotationCenterX":240,"rotationCenterY":180,"skinId":14,"dataFormat":"png","assetId":"739b5e2a2435f6e1ec2993791b423146"},"costumeCount":1,"visible":true,"rotationStyle":"all around","blocks":{},"variables":{"9nCyN5f6o;VaN@]D=otL-count":{"id":"9nCyN5f6o;VaN@]D=otL-count","name":"count","type":"","isCloud":false,"value":0}},"lists":{},"costumes":[{"name":"backdrop1","bitmapResolution":1,"rotationCenterX":240,"rotationCenterY":180,"skinId":14,"dataFormat":"png","assetId":"739b5e2a2435f6e1ec2993791b423146"}],"sounds":[{"name":"pop","format":"","rate":11025,"sampleCount":258,"soundID":1,"md5":"83a9787d4cb6f3b7632b4ddfebf74367.wav","data":null,"dataFormat":"wav","assetId":"83a9787d4cb6f3b7632b4ddfebf74367","soundId":"?6#4)F7:+*K/M8p:{C;}"}]},{"id":"toHcUhOaDm-f2QeUU4=W","name":"Sprite1","isStage":false,"x":0,"y":0,"size":100,"direction":90,"draggable":false,"currentCostume":0,"costume":{"name":"costume1","bitmapResolution":1,"rotationCenterX":47,"rotationCenterY":55,"skinId":12,"dataFormat":"svg","assetId":"09dc888b0b7df19f70d81588ae73420e"},"costumeCount":2,"visible":true,"rotationStyle":"all around","blocks":{")a_u%,U5w%u=5BG}NF;y":{"id":")a_u%,U5w%u=5BG}NF;y","opcode":"event_whenflagclicked","inputs":{},"fields":{},"next":"[1LHb?z!6=X0r-u!kDoR","topLevel":true,"parent":null,"shadow":false,"x":84.5,"y":-43.2499999999996},"5OS#FsJ(Hr-P%p:pDb/1":{"id":"5OS#FsJ(Hr-P%p:pDb/1","opcode":"MicroBit.showicon","inputs":{"ICON":{"name":"ICON","block":"~TUX9-w|y_%Xv4),vJxE","shadow":"~TUX9-w|y_%Xv4),vJxE"}},"fields":{},"next":"A.*z|#1~ns+~*GcdKJ5t","topLevel":false,"parent":"[1LHb?z!6=X0r-u!kDoR","shadow":false,"x":192,"y":263.5000000000004},"~TUX9-w|y_%Xv4),vJxE":{"id":"~TUX9-w|y_%Xv4),vJxE","opcode":"MicroBit.menu.imageMenu","inputs":{},"fields":{"imageMenu":{"name":"imageMenu","value":"HEART"}},"next":null,"topLevel":false,"parent":"5OS#FsJ(Hr-P%p:pDb/1","shadow":true},"[1LHb?z!6=X0r-u!kDoR":{"id":"[1LHb?z!6=X0r-u!kDoR","opcode":"control_forever","inputs":{"SUBSTACK":{"name":"SUBSTACK","block":"5OS#FsJ(Hr-P%p:pDb/1","shadow":null}},"fields":{},"next":null,"topLevel":false,"parent":")a_u%,U5w%u=5BG}NF;y","shadow":false,"x":135.75,"y":368.0000000000007},"A.*z|#1~ns+~*GcdKJ5t":{"id":"A.*z|#1~ns+~*GcdKJ5t","opcode":"control_wait","inputs":{"DURATION":{"name":"DURATION","block":"+L,Nz,%1/fG(4@E)iHw3","shadow":"+L,Nz,%1/fG(4@E)iHw3"}},"fields":{},"next":"d|j%nLEwl7G0)IVVaMT[","topLevel":false,"parent":"5OS#FsJ(Hr-P%p:pDb/1","shadow":false,"x":"-300","y":"38"},"+L,Nz,%1/fG(4@E)iHw3":{"id":"+L,Nz,%1/fG(4@E)iHw3","opcode":"math_positive_number","inputs":{},"fields":{"NUM":{"name":"NUM","value":"1"}},"next":null,"topLevel":false,"parent":"A.*z|#1~ns+~*GcdKJ5t","shadow":true},"d|j%nLEwl7G0)IVVaMT[":{"id":"d|j%nLEwl7G0)IVVaMT[","opcode":"MicroBit.showicon","inputs":{"ICON":{"name":"ICON","block":"j^;+s:NuD+cn1z!FsGb(","shadow":"j^;+s:NuD+cn1z!FsGb("}},"fields":{},"next":"o}I5YZ~/CMWl11B,E#EW","topLevel":false,"parent":"A.*z|#1~ns+~*GcdKJ5t","shadow":false,"x":"208","y":"312"},"j^;+s:NuD+cn1z!FsGb(":{"id":"j^;+s:NuD+cn1z!FsGb(","opcode":"MicroBit.menu.imageMenu","inputs":{},"fields":{"imageMenu":{"name":"imageMenu","value":"HEART_SMALL"}},"next":null,"topLevel":false,"parent":"d|j%nLEwl7G0)IVVaMT[","shadow":true},"o}I5YZ~/CMWl11B,E#EW":{"id":"o}I5YZ~/CMWl11B,E#EW","opcode":"control_wait","inputs":{"DURATION":{"name":"DURATION","block":"lyO+(q=+82%97-]/XW@5","shadow":"lyO+(q=+82%97-]/XW@5"}},"fields":{},"next":"~zi0UG$tJAKH_Wi3G81M","topLevel":false,"parent":"d|j%nLEwl7G0)IVVaMT[","shadow":false},"lyO+(q=+82%97-]/XW@5":{"id":"lyO+(q=+82%97-]/XW@5","opcode":"math_positive_number","inputs":{},"fields":{"NUM":{"name":"NUM","value":"1"}},"next":null,"topLevel":false,"parent":"o}I5YZ~/CMWl11B,E#EW","shadow":true},"~zi0UG$tJAKH_Wi3G81M":{"id":"~zi0UG$tJAKH_Wi3G81M","opcode":"MicroBit.showicon","inputs":{"ICON":{"name":"ICON","block":")hu0iG:kO~Km`;+`=Qw1","shadow":")hu0iG:kO~Km`;+`=Qw1"}},"fields":{},"next":"6[px{xc,nA}2Slp=(C2s","topLevel":false,"parent":"o}I5YZ~/CMWl11B,E#EW","shadow":false,"x":"208","y":"416"},")hu0iG:kO~Km`;+`=Qw1":{"id":")hu0iG:kO~Km`;+`=Qw1","opcode":"MicroBit.menu.imageMenu","inputs":{},"fields":{"imageMenu":{"name":"imageMenu","value":"HAPPY"}},"next":null,"topLevel":false,"parent":"~zi0UG$tJAKH_Wi3G81M","shadow":true},"6[px{xc,nA}2Slp=(C2s":{"id":"6[px{xc,nA}2Slp=(C2s","opcode":"control_wait","inputs":{"DURATION":{"name":"DURATION","block":"][wF@Uy]KFEh7a]!6Y!0","shadow":"][wF@Uy]KFEh7a]!6Y!0"}},"fields":{},"next":"+.~bpznFA~O5BVo}7fdW","topLevel":false,"parent":"~zi0UG$tJAKH_Wi3G81M","shadow":false},"][wF@Uy]KFEh7a]!6Y!0":{"id":"][wF@Uy]KFEh7a]!6Y!0","opcode":"math_positive_number","inputs":{},"fields":{"NUM":{"name":"NUM","value":"1"}},"next":null,"topLevel":false,"parent":"6[px{xc,nA}2Slp=(C2s","shadow":true},"+.~bpznFA~O5BVo}7fdW":{"id":"+.~bpznFA~O5BVo}7fdW","opcode":"MicroBit.showicon","inputs":{"ICON":{"name":"ICON","block":"arez|j#%;|P*!n0@8:8t","shadow":"arez|j#%;|P*!n0@8:8t"}},"fields":{},"next":"t3PqR70vJ/?dNCSrXz7m","topLevel":false,"parent":"6[px{xc,nA}2Slp=(C2s","shadow":false,"x":"208","y":"520"},"arez|j#%;|P*!n0@8:8t":{"id":"arez|j#%;|P*!n0@8:8t","opcode":"MicroBit.menu.imageMenu","inputs":{},"fields":{"imageMenu":{"name":"imageMenu","value":"SMILE"}},"next":null,"topLevel":false,"parent":"+.~bpznFA~O5BVo}7fdW","shadow":true},"t3PqR70vJ/?dNCSrXz7m":{"id":"t3PqR70vJ/?dNCSrXz7m","opcode":"control_wait","inputs":{"DURATION":{"name":"DURATION","block":"%dGK89`p353F!)oSLY%3","shadow":"%dGK89`p353F!)oSLY%3"}},"fields":{},"next":"k506Y[xjdw!coFF~vx!x","topLevel":false,"parent":"+.~bpznFA~O5BVo}7fdW","shadow":false},"%dGK89`p353F!)oSLY%3":{"id":"%dGK89`p353F!)oSLY%3","opcode":"math_positive_number","inputs":{},"fields":{"NUM":{"name":"NUM","value":"1"}},"next":null,"topLevel":false,"parent":"t3PqR70vJ/?dNCSrXz7m","shadow":true},"k506Y[xjdw!coFF~vx!x":{"id":"k506Y[xjdw!coFF~vx!x","opcode":"MicroBit.showicon","inputs":{"ICON":{"name":"ICON","block":"cgTR`/TFcMtMgulrXY;$","shadow":"cgTR`/TFcMtMgulrXY;$"}},"fields":{},"next":"d+!C88lWTe37jrKwtwM)","topLevel":false,"parent":"t3PqR70vJ/?dNCSrXz7m","shadow":false,"x":"208","y":"624"},"cgTR`/TFcMtMgulrXY;$":{"id":"cgTR`/TFcMtMgulrXY;$","opcode":"MicroBit.menu.imageMenu","inputs":{},"fields":{"imageMenu":{"name":"imageMenu","value":"SAD"}},"next":null,"topLevel":false,"parent":"k506Y[xjdw!coFF~vx!x","shadow":true},"d+!C88lWTe37jrKwtwM)":{"id":"d+!C88lWTe37jrKwtwM)","opcode":"control_wait","inputs":{"DURATION":{"name":"DURATION","block":"OB@*3nN7dtUaM(pfE/HE","shadow":"OB@*3nN7dtUaM(pfE/HE"}},"fields":{},"next":"g(Di%EK=4f:WNd`oD2#$","topLevel":false,"parent":"k506Y[xjdw!coFF~vx!x","shadow":false},"OB@*3nN7dtUaM(pfE/HE":{"id":"OB@*3nN7dtUaM(pfE/HE","opcode":"math_positive_number","inputs":{},"fields":{"NUM":{"name":"NUM","value":"1"}},"next":null,"topLevel":false,"parent":"d+!C88lWTe37jrKwtwM)","shadow":true},"g(Di%EK=4f:WNd`oD2#$":{"id":"g(Di%EK=4f:WNd`oD2#$","opcode":"MicroBit.showicon","inputs":{"ICON":{"name":"ICON","block":"66,tzyckQZZ(X$ZNLTS+","shadow":"66,tzyckQZZ(X$ZNLTS+"}},"fields":{},"next":";_ZU.@UEOD!mW.^%P?OI","topLevel":false,"parent":"d+!C88lWTe37jrKwtwM)","shadow":false,"x":"81","y":"535"},"66,tzyckQZZ(X$ZNLTS+":{"id":"66,tzyckQZZ(X$ZNLTS+","opcode":"MicroBit.menu.imageMenu","inputs":{},"fields":{"imageMenu":{"name":"imageMenu","value":"CONFUSED"}},"next":null,"topLevel":false,"parent":"g(Di%EK=4f:WNd`oD2#$","shadow":true},";_ZU.@UEOD!mW.^%P?OI":{"id":";_ZU.@UEOD!mW.^%P?OI","opcode":"control_wait","inputs":{"DURATION":{"name":"DURATION","block":":wpn1[{d}ALR=;.IEGz3","shadow":":wpn1[{d}ALR=;.IEGz3"}},"fields":{},"next":"TGql;DL7LI1M@E/kAM]O","topLevel":false,"parent":"g(Di%EK=4f:WNd`oD2#$","shadow":false},":wpn1[{d}ALR=;.IEGz3":{"id":":wpn1[{d}ALR=;.IEGz3","opcode":"math_positive_number","inputs":{},"fields":{"NUM":{"name":"NUM","value":"1"}},"next":null,"topLevel":false,"parent":";_ZU.@UEOD!mW.^%P?OI","shadow":true},"TGql;DL7LI1M@E/kAM]O":{"id":"TGql;DL7LI1M@E/kAM]O","opcode":"MicroBit.showicon","inputs":{"ICON":{"name":"ICON","block":"C%.HKKKclMJ{op-s,6_a","shadow":"C%.HKKKclMJ{op-s,6_a"}},"fields":{},"next":"(=WDX,B*E4A:|i]P)[Yx","topLevel":false,"parent":";_ZU.@UEOD!mW.^%P?OI","shadow":false,"x":"81","y":"639"},"C%.HKKKclMJ{op-s,6_a":{"id":"C%.HKKKclMJ{op-s,6_a","opcode":"MicroBit.menu.imageMenu","inputs":{},"fields":{"imageMenu":{"name":"imageMenu","value":"ANGRY"}},"next":null,"topLevel":false,"parent":"TGql;DL7LI1M@E/kAM]O","shadow":true},"(=WDX,B*E4A:|i]P)[Yx":{"id":"(=WDX,B*E4A:|i]P)[Yx","opcode":"control_wait","inputs":{"DURATION":{"name":"DURATION","block":"(Obj8^d5t)0SxhL=_rd;","shadow":"(Obj8^d5t)0SxhL=_rd;"}},"fields":{},"next":"SxpApP!J}_xyO|JFeek,","topLevel":false,"parent":"TGql;DL7LI1M@E/kAM]O","shadow":false},"(Obj8^d5t)0SxhL=_rd;":{"id":"(Obj8^d5t)0SxhL=_rd;","opcode":"math_positive_number","inputs":{},"fields":{"NUM":{"name":"NUM","value":"1"}},"next":null,"topLevel":false,"parent":"(=WDX,B*E4A:|i]P)[Yx","shadow":true},"SxpApP!J}_xyO|JFeek,":{"id":"SxpApP!J}_xyO|JFeek,","opcode":"MicroBit.showicon","inputs":{"ICON":{"name":"ICON","block":"ImvYE}J~_Akk]c`C%gI#","shadow":"ImvYE}J~_Akk]c`C%gI#"}},"fields":{},"next":".@;Dv.V[a!P`)EgO06el","topLevel":false,"parent":"(=WDX,B*E4A:|i]P)[Yx","shadow":false,"x":"81","y":"743"},"ImvYE}J~_Akk]c`C%gI#":{"id":"ImvYE}J~_Akk]c`C%gI#","opcode":"MicroBit.menu.imageMenu","inputs":{},"fields":{"imageMenu":{"name":"imageMenu","value":"ASLEEP"}},"next":null,"topLevel":false,"parent":"SxpApP!J}_xyO|JFeek,","shadow":true},".@;Dv.V[a!P`)EgO06el":{"id":".@;Dv.V[a!P`)EgO06el","opcode":"control_wait","inputs":{"DURATION":{"name":"DURATION","block":"59uWU_siA=IVi6!U0@U+","shadow":"59uWU_siA=IVi6!U0@U+"}},"fields":{},"next":"u#wb6V-r{he^U2?.~Yg0","topLevel":false,"parent":"SxpApP!J}_xyO|JFeek,","shadow":false},"59uWU_siA=IVi6!U0@U+":{"id":"59uWU_siA=IVi6!U0@U+","opcode":"math_positive_number","inputs":{},"fields":{"NUM":{"name":"NUM","value":"1"}},"next":null,"topLevel":false,"parent":".@;Dv.V[a!P`)EgO06el","shadow":true},"u#wb6V-r{he^U2?.~Yg0":{"id":"u#wb6V-r{he^U2?.~Yg0","opcode":"MicroBit.showicon","inputs":{"ICON":{"name":"ICON","block":"9AQ{9yP!wR?ZaAI?AIB#","shadow":"9AQ{9yP!wR?ZaAI?AIB#"}},"fields":{},"next":"Ly6`KQk1zPQ.b1b[N,yo","topLevel":false,"parent":".@;Dv.V[a!P`)EgO06el","shadow":false,"x":"81","y":"847"},"9AQ{9yP!wR?ZaAI?AIB#":{"id":"9AQ{9yP!wR?ZaAI?AIB#","opcode":"MicroBit.menu.imageMenu","inputs":{},"fields":{"imageMenu":{"name":"imageMenu","value":"SURPRISED"}},"next":null,"topLevel":false,"parent":"u#wb6V-r{he^U2?.~Yg0","shadow":true},"Ly6`KQk1zPQ.b1b[N,yo":{"id":"Ly6`KQk1zPQ.b1b[N,yo","opcode":"control_wait","inputs":{"DURATION":{"name":"DURATION","block":"F2xy*`rq.gp$SJf4h`_@","shadow":"F2xy*`rq.gp$SJf4h`_@"}},"fields":{},"next":"xjB@3DHc+3cc1/nXdiW0","topLevel":false,"parent":"u#wb6V-r{he^U2?.~Yg0","shadow":false},"F2xy*`rq.gp$SJf4h`_@":{"id":"F2xy*`rq.gp$SJf4h`_@","opcode":"math_positive_number","inputs":{},"fields":{"NUM":{"name":"NUM","value":"1"}},"next":null,"topLevel":false,"parent":"Ly6`KQk1zPQ.b1b[N,yo","shadow":true},"xjB@3DHc+3cc1/nXdiW0":{"id":"xjB@3DHc+3cc1/nXdiW0","opcode":"MicroBit.showicon","inputs":{"ICON":{"name":"ICON","block":"a65(lPrYp@,E8?xKaz6z","shadow":"a65(lPrYp@,E8?xKaz6z"}},"fields":{},"next":"Pe=q-sb#s_Gsp+:Bb*{2","topLevel":false,"parent":"Ly6`KQk1zPQ.b1b[N,yo","shadow":false,"x":"81","y":"951"},"a65(lPrYp@,E8?xKaz6z":{"id":"a65(lPrYp@,E8?xKaz6z","opcode":"MicroBit.menu.imageMenu","inputs":{},"fields":{"imageMenu":{"name":"imageMenu","value":"SILLY"}},"next":null,"topLevel":false,"parent":"xjB@3DHc+3cc1/nXdiW0","shadow":true},"Pe=q-sb#s_Gsp+:Bb*{2":{"id":"Pe=q-sb#s_Gsp+:Bb*{2","opcode":"control_wait","inputs":{"DURATION":{"name":"DURATION","block":"m_KB#!-mztUJE2Mo|[Rl","shadow":"m_KB#!-mztUJE2Mo|[Rl"}},"fields":{},"next":"],#*[gkx3pQl{8g@okOR","topLevel":false,"parent":"xjB@3DHc+3cc1/nXdiW0","shadow":false},"m_KB#!-mztUJE2Mo|[Rl":{"id":"m_KB#!-mztUJE2Mo|[Rl","opcode":"math_positive_number","inputs":{},"fields":{"NUM":{"name":"NUM","value":"1"}},"next":null,"topLevel":false,"parent":"Pe=q-sb#s_Gsp+:Bb*{2","shadow":true},"],#*[gkx3pQl{8g@okOR":{"id":"],#*[gkx3pQl{8g@okOR","opcode":"MicroBit.showicon","inputs":{"ICON":{"name":"ICON","block":"*)xKx1Ja:1LY3!X!@2Me","shadow":"*)xKx1Ja:1LY3!X!@2Me"}},"fields":{},"next":".4+?Y6ey%@)?aMT~!97)","topLevel":false,"parent":"Pe=q-sb#s_Gsp+:Bb*{2","shadow":false,"x":"81","y":"1055"},"*)xKx1Ja:1LY3!X!@2Me":{"id":"*)xKx1Ja:1LY3!X!@2Me","opcode":"MicroBit.menu.imageMenu","inputs":{},"fields":{"imageMenu":{"name":"imageMenu","value":"YES"}},"next":null,"topLevel":false,"parent":"],#*[gkx3pQl{8g@okOR","shadow":true},".4+?Y6ey%@)?aMT~!97)":{"id":".4+?Y6ey%@)?aMT~!97)","opcode":"control_wait","inputs":{"DURATION":{"name":"DURATION","block":"L3AU8tX-):@ZS)[O/0WF","shadow":"L3AU8tX-):@ZS)[O/0WF"}},"fields":{},"next":"Rpuv?pDcH@+/MSDY9D6h","topLevel":false,"parent":"],#*[gkx3pQl{8g@okOR","shadow":false},"L3AU8tX-):@ZS)[O/0WF":{"id":"L3AU8tX-):@ZS)[O/0WF","opcode":"math_positive_number","inputs":{},"fields":{"NUM":{"name":"NUM","value":"1"}},"next":null,"topLevel":false,"parent":".4+?Y6ey%@)?aMT~!97)","shadow":true},"Rpuv?pDcH@+/MSDY9D6h":{"id":"Rpuv?pDcH@+/MSDY9D6h","opcode":"MicroBit.showicon","inputs":{"ICON":{"name":"ICON","block":"^WwQVP,V0*HrhzPt@C,0","shadow":"^WwQVP,V0*HrhzPt@C,0"}},"fields":{},"next":"~,p}3[V~*81znT0GdXh-","topLevel":false,"parent":".4+?Y6ey%@)?aMT~!97)","shadow":false,"x":"81","y":"1159"},"^WwQVP,V0*HrhzPt@C,0":{"id":"^WwQVP,V0*HrhzPt@C,0","opcode":"MicroBit.menu.imageMenu","inputs":{},"fields":{"imageMenu":{"name":"imageMenu","value":"NO"}},"next":null,"topLevel":false,"parent":"Rpuv?pDcH@+/MSDY9D6h","shadow":true},"~,p}3[V~*81znT0GdXh-":{"id":"~,p}3[V~*81znT0GdXh-","opcode":"control_wait","inputs":{"DURATION":{"name":"DURATION","block":"sZ0us(o*K22Gzg`H$9AR","shadow":"sZ0us(o*K22Gzg`H$9AR"}},"fields":{},"next":null,"topLevel":false,"parent":"Rpuv?pDcH@+/MSDY9D6h","shadow":false},"sZ0us(o*K22Gzg`H$9AR":{"id":"sZ0us(o*K22Gzg`H$9AR","opcode":"math_positive_number","inputs":{},"fields":{"NUM":{"name":"NUM","value":"1"}},"next":null,"topLevel":false,"parent":"~,p}3[V~*81znT0GdXh-","shadow":true}},"variables":{},"lists":{},"costumes":[{"name":"costume1","bitmapResolution":1,"rotationCenterX":47,"rotationCenterY":55,"skinId":12,"dataFormat":"svg","assetId":"09dc888b0b7df19f70d81588ae73420e"},{"name":"costume2","bitmapResolution":1,"rotationCenterX":47,"rotationCenterY":55,"skinId":13,"dataFormat":"svg","assetId":"3696356a03a8d938318876a593572843"}],"sounds":[{"name":"Meow","format":"","rate":22050,"sampleCount":18688,"soundID":0,"md5":"83c36d806dc92327b9e7049a565c6bff.wav","data":null,"dataFormat":"wav","assetId":"83c36d806dc92327b9e7049a565c6bff","soundId":"8^(!|=^zVAkuh[VlzW;R"}]}],"meta":{"semver":"3.0.0","vm":"0.1.0","agent":"Mozilla/5.0 (Windows NT 6.1; WOW64) AppleWebKit/537.36 (KHTML, like Gecko) Kittenblock/1.6.1 Chrome/58.0.3029.110 Electron/1.7.10 Safari/537.36"}}